web_etc/__init__.py
web_etc/main.py
web_etc/templates/index.html
web_etc/templates/login.html
web_etc-0.2.0.dist-info/METADATA
web_etc-0.2.0.dist-info/WHEEL
web_etc-0.2.0.dist-info/RECORD
